onegov.file-0.13.5-py3.6-nspkg.pth
onegov/file/.gitignore
onegov/file/__init__.py
onegov/file/attachments.py
onegov/file/collection.py
onegov/file/errors.py
onegov/file/filters.py
onegov/file/integration.py
onegov/file/upgrade.py
onegov/file/utils.py
onegov/file/models/__init__.py
onegov/file/models/associated_files.py
onegov/file/models/file.py
onegov/file/models/file_message.py
onegov/file/models/fileset.py
onegov/file/sign/__init__.py
onegov/file/sign/generic.py
onegov/file/sign/swisscom_ais.py
onegov/file/tests/conftest.py
onegov/file/tests/test_collection.py
onegov/file/tests/test_integration.py
onegov/file/tests/test_models.py
onegov/file/tests/test_utils.py
onegov/file/tests/cassettes/ais-error.json
onegov/file/tests/cassettes/ais-success.json
onegov/file/tests/fixtures/bomb.png
onegov/file/tests/fixtures/example.docx
onegov/file/tests/fixtures/example.pdf
onegov/file/tests/fixtures/sample.pdf
onegov/file/tests/fixtures/test.crt
onegov/file/tests/fixtures/test.key
onegov.file-0.13.5.dist-info/METADATA
onegov.file-0.13.5.dist-info/WHEEL
onegov.file-0.13.5.dist-info/entry_points.txt
onegov.file-0.13.5.dist-info/namespace_packages.txt
onegov.file-0.13.5.dist-info/top_level.txt
onegov.file-0.13.5.dist-info/RECORD
