Metadata-Version: 2.1
Name: onegov.file
Version: 0.13.5
Summary: Images/files organized in collections.
Home-page: http://github.com/OneGov/onegov.file
Author: Seantis GmbH
Author-email: info@seantis.ch
License: GPLv2
Platform: any
Classifier: Intended Audience :: Developers
Classifier: Programming Language :: Python :: 3 :: Only
Classifier: Programming Language :: Python :: 3.6
Classifier: Programming Language :: Python :: 3.7
Classifier: Topic :: Software Development :: Libraries :: Python Modules
Classifier: License :: OSI Approved :: GNU General Public License v2 (GPLv2)
Requires-Python: >=3.6
Requires-Dist: AIS.py (>=0.2.2)
Requires-Dist: filedepot (>=0.6.0)
Requires-Dist: isodate
Requires-Dist: lxml
Requires-Dist: more.transaction
Requires-Dist: onegov.chat
Requires-Dist: onegov.core (>=0.4.0)
Requires-Dist: onegov.search
Requires-Dist: pdftotext
Requires-Dist: Pillow (!=5.4.0)
Requires-Dist: python-magic
Requires-Dist: sedate
Requires-Dist: sqlalchemy
Requires-Dist: sqlalchemy-utils
Requires-Dist: webob
Provides-Extra: test
Requires-Dist: coverage ; extra == 'test'
Requires-Dist: onegov-testing ; extra == 'test'
Requires-Dist: vcrpy ; extra == 'test'
Requires-Dist: pytest ; extra == 'test'
